{
    "$schema": "http://schema.management.azure.com/schemas/2015-01-01/deploymentParameters.json#",
    "contentVersion": "1.0.0.0",
    "parameters": {
        "name": {
            "value": "devbot"
        },
        "zipUrl":{
            "value": "https://zipurlhere"
        },
        "microsoftAppId": {
            "value": "<AppIDHere>"
        },
        "microsoftAppKey": {
            "value": "<AppKeyHere>"
        },
        "luisApplicationId": {
            "value": "<LUISApplicationIdHere>"
        }
    }
}